setup.py
src/digimat/__init__.py
src/digimat.danfossxml.egg-info/PKG-INFO
src/digimat.danfossxml.egg-info/SOURCES.txt
src/digimat.danfossxml.egg-info/dependency_links.txt
src/digimat.danfossxml.egg-info/namespace_packages.txt
src/digimat.danfossxml.egg-info/not-zip-safe
src/digimat.danfossxml.egg-info/requires.txt
src/digimat.danfossxml.egg-info/top_level.txt
src/digimat/danfossxml/__init__.py
src/digimat/danfossxml/danfossxml.py