Metadata-Version: 1.0
Name: digimat.danfossxml
Version: 0.1.5
Summary: Digimat Danfoss XML
Home-page: UNKNOWN
Author: Frederic Hess
Author-email: fhess@splust.ch
License: PSF
Platform: UNKNOWN
